teamtalk/__init__.py
teamtalk/_utils.py
teamtalk/audio.py
teamtalk/bot.py
teamtalk/channel.py
teamtalk/device.py
teamtalk/download_sdk.py
teamtalk/enums.py
teamtalk/exceptions.py
teamtalk/instance.py
teamtalk/message.py
teamtalk/permission.py
teamtalk/server.py
teamtalk/statistics.py
teamtalk/streamer.py
teamtalk/subscription.py
teamtalk/tt_file.py
teamtalk/user.py
teamtalk/user_account.py
teamtalk/implementation/__init__.py
teamtalk/tools/__init__.py
teamtalk/tools/downloader.py
teamtalk/tools/ttsdk_downloader.py
teamtalk_py-1.4.0.dist-info/licenses/LICENSE
teamtalk_py-1.4.0.dist-info/METADATA
teamtalk_py-1.4.0.dist-info/WHEEL
teamtalk_py-1.4.0.dist-info/top_level.txt
teamtalk_py-1.4.0.dist-info/RECORD
