Metadata-Version: 2.4
Name: teamtalk-py
Version: 1.4.0
Summary: a simple but powerful pythonic library for making bots for the TeamTalk5 Conferencing System
Author-email: JessicaTegner <jessica.tegner@outlook.com>
License: MIT
Project-URL: Issue Tracker, https://github.com/JessicaTegner/teamtalk.py/issues/
Keywords: teamtalk,teamtalk5,teamtalk sdk,conferencing
Classifier: Development Status :: 4 - Beta
Classifier: Framework :: AsyncIO
Classifier: Natural Language :: English
Classifier: Operating System :: OS Independent
Classifier: Topic :: Internet
Classifier: Topic :: Software Development :: Libraries
Classifier: Topic :: Software Development :: Libraries :: Python Modules
Classifier: Topic :: Utilities
Classifier: Typing :: Typed
Requires-Python: >=3.11
License-File: LICENSE
Requires-Dist: beautifulsoup4>=4.12
Requires-Dist: patool>=3.0
Requires-Dist: requests>=2.32
Requires-Dist: typing-extensions>=4.12
Provides-Extra: docs
Requires-Dist: sphinx-sitemap>=2.6; extra == "docs"
Requires-Dist: sphinx>=8.1; extra == "docs"
Requires-Dist: sphinxcontrib-napoleon>=0.7; extra == "docs"
Requires-Dist: sphinxcontrib-trio>=1.1; extra == "docs"
Dynamic: license-file
